julep_ai/__init__.py
julep_ai/api/__init__.py
julep_ai/api/client.py
julep_ai/api/core/__init__.py
julep_ai/api/core/api_error.py
julep_ai/api/core/client_wrapper.py
julep_ai/api/core/datetime_utils.py
julep_ai/api/core/jsonable_encoder.py
julep_ai/api/core/remove_none_from_dict.py
julep_ai/api/environment.py
julep_ai/api/types/__init__.py
julep_ai/api/types/additional_info.py
julep_ai/api/types/agent.py
julep_ai/api/types/agent_default_settings.py
julep_ai/api/types/belief.py
julep_ai/api/types/chat_input_data.py
julep_ai/api/types/chat_ml_message.py
julep_ai/api/types/chat_ml_message_role.py
julep_ai/api/types/chat_response.py
julep_ai/api/types/chat_response_finish_reason.py
julep_ai/api/types/chat_settings.py
julep_ai/api/types/chat_settings_response_format.py
julep_ai/api/types/chat_settings_response_format_type.py
julep_ai/api/types/chat_settings_stop.py
julep_ai/api/types/completion_usage.py
julep_ai/api/types/create_additional_info_request.py
julep_ai/api/types/create_tool_request.py
julep_ai/api/types/create_tool_request_type.py
julep_ai/api/types/entity.py
julep_ai/api/types/episode.py
julep_ai/api/types/function_call_option.py
julep_ai/api/types/function_def.py
julep_ai/api/types/function_parameters.py
julep_ai/api/types/get_agent_additional_info_response.py
julep_ai/api/types/get_agent_memories_response.py
julep_ai/api/types/get_agent_tools_response.py
julep_ai/api/types/get_history_response.py
julep_ai/api/types/get_suggestions_response.py
julep_ai/api/types/get_user_additional_info_response.py
julep_ai/api/types/input_chat_ml_message.py
julep_ai/api/types/input_chat_ml_message_role.py
julep_ai/api/types/instruction.py
julep_ai/api/types/list_agents_response.py
julep_ai/api/types/list_sessions_response.py
julep_ai/api/types/list_users_response.py
julep_ai/api/types/memory.py
julep_ai/api/types/memory_access_options.py
julep_ai/api/types/named_tool_choice.py
julep_ai/api/types/named_tool_choice_function.py
julep_ai/api/types/resource_created_response.py
julep_ai-0.1.0.dist-info/METADATA
julep_ai-0.1.0.dist-info/WHEEL
julep_ai-0.1.0.dist-info/RECORD
